django_deploy_tools/__init__.py
django_deploy_tools/apps.py
django_deploy_tools/asgi.py
django_deploy_tools/settings.py
django_deploy_tools/tests.py
django_deploy_tools/urls.py
django_deploy_tools/wsgi.py
django_deploy_tools/management/__init__.py
django_deploy_tools/management/commands/__init__.py
django_deploy_tools/management/commands/make_apache_conf.py
django_deploy_tools/management/commands/make_sgi.py
django_deploy_tools/templates/django_deploy_tools/apache_vhost.conf
django_deploy_tools/templates/django_deploy_tools/sgi.py
django_deploy_tools/utils/__init__.py
django_deploy_tools/utils/apache.py
Django_Deployment_Tools-0.5.0.dist-info/AUTHORS
Django_Deployment_Tools-0.5.0.dist-info/LICENCE
Django_Deployment_Tools-0.5.0.dist-info/METADATA
Django_Deployment_Tools-0.5.0.dist-info/WHEEL
Django_Deployment_Tools-0.5.0.dist-info/pbr.json
Django_Deployment_Tools-0.5.0.dist-info/top_level.txt
Django_Deployment_Tools-0.5.0.dist-info/RECORD
